kumiho_comfyui-1.0.1.dist-info/licenses/LICENSE
kumiho_nodes/__init__.py
kumiho_nodes/nodes.py
kumiho_nodes/utils.py
kumiho_comfyui-1.0.1.dist-info/METADATA
kumiho_comfyui-1.0.1.dist-info/WHEEL
kumiho_comfyui-1.0.1.dist-info/top_level.txt
kumiho_comfyui-1.0.1.dist-info/RECORD
