Metadata-Version: 2.4
Name: kumiho-comfyui
Version: 1.0.1
Summary: Kumiho ComfyUI custom nodes - Connect ComfyUI workflows with Kumiho Cloud asset management system
License: MIT License
Project-URL: Homepage, https://kumiho.io
Project-URL: Repository, https://github.com/kumihoclouds/kumiho-comfyui
Project-URL: Documentation, https://docs.kumiho.io
Requires-Python: >=3.10
License-File: LICENSE
Requires-Dist: torch
Requires-Dist: numpy
Requires-Dist: Pillow
Requires-Dist: requests
Requires-Dist: aiohttp
Requires-Dist: kumiho
Dynamic: license-file
